{"arenas":[{"foods":["Mustard Ice Cream","Mallowicious Bar","Wriggling Grub","Apple Onion Rings","Wild Chocomato","Sushi","Grapity Slush","Eye Candy","Strochal","Cheese and Tomato Sub"],"ratio":"-22.2%","name":"Shipwreck","pirates":["Ol' Stripey","Stuff-A-Roo","Squire Venable","Admiral Blackbeard"]},{"foods":["Hot Cakes","Fungi Pizza","Strochal","Flaming Fire Faerie Pizza","Sushi","Wild Chocomato","Super Lemon Grape Slush","Worm and Leech Pizza","Rasmelon","Asparagus Pie"],"ratio":"-18.9%","name":"Lagoon","pirates":["Sir Edmund Ogletree","Orvinn the First Mate","The Tailhook Kid","Franchisco Corvallio"]},{"foods":["Fungi Pizza","Rainbow Negg","Eye Candy","Ice Chocolate Cake","Ultimate Burger","Orange Negg","Fish Negg","Worm and Leech Pizza","Wriggling Grub","Hot Tyrannian Pepper"],"ratio":"-7.1%","name":"Treasure Island","pirates":["Puffo the Waister","Fairfax the Deckhand","Bonnie Pip Culliford","Lucky McKyriggan"]},{"foods":["Grapity Slush","Fungi Pizza","Flaming Burnumup","Broccoli and Cheese Pizza","Negg Stew","Fresh Seaweed Pie","Spicy Wings","Cheese and Tomato Sub","Super Lemon Grape Slush","Hotfish"],"ratio":"-24.6%","name":"Hidden Cove","pirates":["Gooblah the Grarrl","Young Sproggie","Federismo Corvallio","Buck Cutlass"]},{"foods":["Apple Onion Rings","Broccoli","Broccoli and Cheese Pizza","Hot Tyrannian Pepper","Ice Chocolate Cake","Lemon Blitz","Wild Chocomato","Negg Stew","Sushi","Spicy Wings"],"ratio":"+22%","name":"Harpoon Harry's","pirates":["Scurvy Dan the Blade","Peg Leg Percival","Ned the Skipper","Captain Crossblades"]}],"round":5545,"pirates":[{"payout":"-26.8%","strength":74,"name":"Ol' Stripey","weight":189,"opening":"2:1","current":"2:1","fa":"+1","probability":"36.6%","won":false},{"payout":"-6.2%","strength":59,"name":"Stuff-A-Roo","weight":211,"opening":"7:1","current":"7:1","fa":"+0","probability":"13.4%","won":false},{"payout":"-6.2%","strength":61,"name":"Squire Venable","weight":213,"opening":"7:1","current":"7:1","fa":"-1","probability":"13.4%","won":false},{"payout":"-26.8%","strength":76,"name":"Admiral Blackbeard","weight":171,"opening":"2:1","current":"2:1","fa":"-1","probability":"36.6%","won":true},{"payout":"-6.2%","strength":79,"name":"Sir Edmund Ogletree","weight":177,"opening":"7:1","current":"7:1","fa":"+1","probability":"13.4%","won":false},{"payout":"-4.2%","strength":52,"name":"Orvinn the First Mate","weight":221,"opening":"11:1","current":"11:1","fa":"+5","probability":"8.7%","won":false},{"payout":"-22.1%","strength":81,"name":"The Tailhook Kid","weight":207,"opening":"2:1","current":"2:1","fa":"+2","probability":"38.9%","won":false},{"payout":"-22.1%","strength":81,"name":"Franchisco Corvallio","weight":165,"opening":"2:1","current":"2:1","fa":"+1","probability":"38.9%","won":true},{"payout":"-35.0%","strength":68,"name":"Puffo the Waister","weight":180,"opening":"13:1","current":"13:1","fa":"+1","probability":"5.0%","won":false},{"payout":"-7.1%","strength":71,"name":"Fairfax the Deckhand","weight":151,"opening":"6:1","current":"6:1","fa":"+1","probability":"15.5%","won":true},{"payout":"-12.5%","strength":76,"name":"Bonnie Pip Culliford","weight":116,"opening":"3:1","current":"3:1","fa":"+1","probability":"29.2%","won":false},{"payout":"+0.7%","strength":82,"name":"Lucky McKyriggan","weight":182,"opening":"2:1","current":"2:1","fa":"+2","probability":"50.4%","won":false},{"payout":"-27.5%","strength":93,"name":"Gooblah the Grarrl","weight":199,"opening":"2:1","current":"2:1","fa":"+0","probability":"36.3%","won":false},{"payout":"-35.0%","strength":73,"name":"Young Sproggie","weight":112,"opening":"13:1","current":"13:1","fa":"+1","probability":"5.0%","won":false},{"payout":"-27.5%","strength":81,"name":"Federismo Corvallio","weight":166,"opening":"2:1","current":"2:1","fa":"+3","probability":"36.3%","won":true},{"payout":"-10.0%","strength":89,"name":"Buck Cutlass","weight":189,"opening":"4:1","current":"4:1","fa":"-2","probability":"22.5%","won":false},{"payout":"+17.5%","strength":87,"name":"Scurvy Dan the Blade","weight":166,"opening":"2:1","current":"2:1","fa":"+1","probability":"58.7%","won":true},{"payout":"+24.1%","strength":73,"name":"Peg Leg Percival","weight":202,"opening":"10:1","current":"13:1","fa":"+0","probability":"9.5%","won":false},{"payout":"+28.3%","strength":79,"name":"Ned the Skipper","weight":169,"opening":"5:1","current":"7:1","fa":"-1","probability":"18.3%","won":false},{"payout":"+33.9%","strength":66,"name":"Captain Crossblades","weight":185,"opening":"7:1","current":"10:1","fa":"+0","probability":"13.4%","won":false}]}