{"arenas":[{"foods":["Bubbling Blueberry Pizza","Rasmelon","Cinnamon Swirl","Cheese and Tomato Sub","Rainborific Slush","Anchovies","Tangy Tropic Slush","Orange Negg","Fish Negg","Wriggling Grub"],"ratio":"-21.1%","name":"Shipwreck","pirates":["Lucky McKyriggan","Captain Crossblades","Bonnie Pip Culliford","Young Sproggie"]},{"foods":["Cinnamon Swirl","Rainbow Negg","Worm and Leech Pizza","Blueberry Tomato Blend","Hot Tyrannian Pepper","Sushi","Lemon Blitz","Mustard Ice Cream","Rainborific Slush","Super Lemon Grape Slush"],"ratio":"-15.8%","name":"Lagoon","pirates":["Ol' Stripey","Scurvy Dan the Blade","Orvinn the First Mate","Federismo Corvallio"]},{"foods":["Rasmelon","Hotfish","Flaming Fire Faerie Pizza","Strochal","Ultimate Burger","Streaky Bacon","Lemon Blitz","Joint Of Ham","Bubbling Blueberry Pizza","Broccoli and Cheese Pizza"],"ratio":"+28.4%","name":"Treasure Island","pirates":["Gooblah the Grarrl","Fairfax the Deckhand","Buck Cutlass","Sir Edmund Ogletree"]},{"foods":["Asparagus Pie","Hot Tyrannian Pepper","Rasmelon","Lemon Blitz","Hotfish","Flaming Fire Faerie Pizza","Bubbling Blueberry Pizza","Wild Chocomato","Apple Onion Rings","Spicy Wings"],"ratio":"+1.3%","name":"Hidden Cove","pirates":["Puffo the Waister","The Tailhook Kid","Admiral Blackbeard","Squire Venable"]},{"foods":["Cinnamon Swirl","Wild Chocomato","Cheese and Tomato Sub","Super Lemon Grape Slush","Tangy Tropic Slush","Apple Onion Rings","Fish Negg","Grapity Slush","Spicy Wings","Mustard Ice Cream"],"ratio":"+23.4%","name":"Harpoon Harry's","pirates":["Ned the Skipper","Peg Leg Percival","Stuff-A-Roo","Franchisco Corvallio"]}],"round":5951,"pirates":[{"payout":"-14.2%","strength":82,"name":"Lucky McKyriggan","weight":182,"opening":"3:1","current":"3:1","fa":"+0","probability":"28.6%","won":true},{"payout":"-5.2%","strength":66,"name":"Captain Crossblades","weight":185,"opening":"10:1","current":"10:1","fa":"+2","probability":"9.5%","won":false},{"payout":"-14.2%","strength":76,"name":"Bonnie Pip Culliford","weight":116,"opening":"3:1","current":"3:1","fa":"+2","probability":"28.6%","won":false},{"payout":"-33.3%","strength":73,"name":"Young Sproggie","weight":112,"opening":"2:1","current":"2:1","fa":"+2","probability":"33.3%","won":false},{"payout":"-5.0%","strength":74,"name":"Ol' Stripey","weight":189,"opening":"9:1","current":"9:1","fa":"+2","probability":"10.6%","won":false},{"payout":"-15.6%","strength":87,"name":"Scurvy Dan the Blade","weight":166,"opening":"2:1","current":"2:1","fa":"+0","probability":"42.2%","won":false},{"payout":"-35.0%","strength":52,"name":"Orvinn the First Mate","weight":221,"opening":"13:1","current":"13:1","fa":"+2","probability":"5.0%","won":false},{"payout":"-15.6%","strength":81,"name":"Federismo Corvallio","weight":166,"opening":"2:1","current":"2:1","fa":"+0","probability":"42.2%","won":true},{"payout":"+37.9%","strength":93,"name":"Gooblah the Grarrl","weight":199,"opening":"2:1","current":"2:1","fa":"+4","probability":"69.0%","won":true},{"payout":"-35.0%","strength":71,"name":"Fairfax the Deckhand","weight":151,"opening":"13:1","current":"13:1","fa":"+3","probability":"5.0%","won":false},{"payout":"+16.1%","strength":89,"name":"Buck Cutlass","weight":189,"opening":"9:1","current":"11:1","fa":"-1","probability":"10.6%","won":false},{"payout":"+39.3%","strength":79,"name":"Sir Edmund Ogletree","weight":177,"opening":"6:1","current":"9:1","fa":"+3","probability":"15.5%","won":false},{"payout":"-35.0%","strength":68,"name":"Puffo the Waister","weight":180,"opening":"13:1","current":"13:1","fa":"+1","probability":"5.0%","won":true},{"payout":"+21.7%","strength":81,"name":"The Tailhook Kid","weight":207,"opening":"2:1","current":"2:1","fa":"+3","probability":"60.8%","won":false},{"payout":"-12.5%","strength":76,"name":"Admiral Blackbeard","weight":171,"opening":"3:1","current":"3:1","fa":"+3","probability":"29.2%","won":false},{"payout":"-35.0%","strength":61,"name":"Squire Venable","weight":213,"opening":"13:1","current":"13:1","fa":"-3","probability":"5.0%","won":false},{"payout":"+16.1%","strength":79,"name":"Ned the Skipper","weight":169,"opening":"9:1","current":"11:1","fa":"-2","probability":"10.6%","won":false},{"payout":"+28.3%","strength":73,"name":"Peg Leg Percival","weight":202,"opening":"5:1","current":"7:1","fa":"+0","probability":"18.3%","won":false},{"payout":"-35.0%","strength":59,"name":"Stuff-A-Roo","weight":211,"opening":"13:1","current":"13:1","fa":"-1","probability":"5.0%","won":false},{"payout":"+32.2%","strength":81,"name":"Franchisco Corvallio","weight":165,"opening":"2:1","current":"2:1","fa":"+0","probability":"66.1%","won":true}]}