{"arenas":[{"foods":["Super Lemon Grape Slush","Negg Stew","Joint Of Ham","Fish Negg","Ice Chocolate Cake","Strochal","Fresh Seaweed Pie","Broccoli","Wriggling Grub","Eye Candy"],"ratio":"+36.8%","name":"Shipwreck","pirates":["Franchisco Corvallio","Captain Crossblades","Young Sproggie","Buck Cutlass"]},{"foods":["Cheese and Tomato Sub","Eye Candy","Rasmelon","Apple Onion Rings","Bubbling Blueberry Pizza","Hot Cakes","Fresh Seaweed Pie","Super Lemon Grape Slush","Broccoli and Cheese Pizza","Joint Of Ham"],"ratio":"-3.4%","name":"Lagoon","pirates":["Squire Venable","Puffo the Waister","Orvinn the First Mate","Peg Leg Percival"]},{"foods":["Flaming Fire Faerie Pizza","Hotfish","Orange Negg","Negg Stew","Hot Cakes","Anchovies","Rainbow Negg","Eye Candy","Mallowicious Bar","Grapity Slush"],"ratio":"-7.1%","name":"Treasure Island","pirates":["Ned the Skipper","Admiral Blackbeard","Fairfax the Deckhand","Scurvy Dan the Blade"]},{"foods":["Orange Negg","Fungi Pizza","Negg Stew","Joint Of Ham","Wild Chocomato","Sushi","Hotfish","Rainborific Slush","Hot Cakes","Ice Chocolate Cake"],"ratio":"+36.8%","name":"Hidden Cove","pirates":["Ol' Stripey","Sir Edmund Ogletree","Lucky McKyriggan","Gooblah the Grarrl"]},{"foods":["Ultimate Burger","Strochal","Flaming Burnumup","Sushi","Fungi Pizza","Cinnamon Swirl","Asparagus Pie","Rasmelon","Bubbling Blueberry Pizza","Flaming Fire Faerie Pizza"],"ratio":"-18.4%","name":"Harpoon Harry's","pirates":["Bonnie Pip Culliford","The Tailhook Kid","Federismo Corvallio","Stuff-A-Roo"]}],"round":5993,"pirates":[{"payout":"-35.0%","strength":"","name":"Franchisco Corvallio","weight":"","opening":"13:1","current":"13:1","fa":"-2","probability":"5.0%","won":false},{"payout":"-35.0%","strength":"","name":"Captain Crossblades","weight":"","opening":"13:1","current":"13:1","fa":"+0","probability":"5.0%","won":false},{"payout":"-35.0%","strength":"","name":"Young Sproggie","weight":"","opening":"13:1","current":"13:1","fa":"+0","probability":"5.0%","won":true},{"payout":"+70.0%","strength":"","name":"Buck Cutlass","weight":"","opening":"2:1","current":"2:1","fa":"+2","probability":"85.0%","won":false},{"payout":"-35.0%","strength":"","name":"Squire Venable","weight":"","opening":"13:1","current":"13:1","fa":"-1","probability":"5.0%","won":false},{"payout":"-12.5%","strength":"","name":"Puffo the Waister","weight":"","opening":"3:1","current":"3:1","fa":"+2","probability":"29.2%","won":false},{"payout":"-5.6%","strength":"","name":"Orvinn the First Mate","weight":"","opening":"8:1","current":"8:1","fa":"+1","probability":"11.8%","won":false},{"payout":"+8.1%","strength":"","name":"Peg Leg Percival","weight":"","opening":"2:1","current":"2:1","fa":"-1","probability":"54.0%","won":true},{"payout":"-12.5%","strength":"","name":"Ned the Skipper","weight":"","opening":"3:1","current":"3:1","fa":"+2","probability":"29.2%","won":false},{"payout":"-7.1%","strength":"","name":"Admiral Blackbeard","weight":"","opening":"6:1","current":"6:1","fa":"+1","probability":"15.5%","won":false},{"payout":"-35.0%","strength":"","name":"Fairfax the Deckhand","weight":"","opening":"13:1","current":"13:1","fa":"-1","probability":"5.0%","won":false},{"payout":"+0.7%","strength":"","name":"Scurvy Dan the Blade","weight":"","opening":"2:1","current":"2:1","fa":"+0","probability":"50.4%","won":true},{"payout":"+4.2%","strength":"","name":"Ol' Stripey","weight":"","opening":"12:1","current":"13:1","fa":"+3","probability":"8.0%","won":false},{"payout":"-35.0%","strength":"","name":"Sir Edmund Ogletree","weight":"","opening":"13:1","current":"13:1","fa":"+0","probability":"5.0%","won":false},{"payout":"-35.0%","strength":"","name":"Lucky McKyriggan","weight":"","opening":"13:1","current":"13:1","fa":"+0","probability":"5.0%","won":false},{"payout":"+64.0%","strength":"","name":"Gooblah the Grarrl","weight":"","opening":"2:1","current":"2:1","fa":"+2","probability":"82.0%","won":true},{"payout":"-5.6%","strength":"","name":"Bonnie Pip Culliford","weight":"","opening":"8:1","current":"8:1","fa":"+1","probability":"11.8%","won":false},{"payout":"-21.4%","strength":"","name":"The Tailhook Kid","weight":"","opening":"2:1","current":"2:1","fa":"+3","probability":"39.3%","won":false},{"payout":"-21.4%","strength":"","name":"Federismo Corvallio","weight":"","opening":"2:1","current":"2:1","fa":"+2","probability":"39.3%","won":true},{"payout":"-4.5%","strength":"","name":"Stuff-A-Roo","weight":"","opening":"10:1","current":"10:1","fa":"+3","probability":"9.5%","won":false}]}