{"arenas":[{"foods":["Lemon Blitz","Orange Negg","Asparagus Pie","Cheese and Tomato Sub","Ice Chocolate Cake","Cinnamon Swirl","Hot Cakes","Sushi","Grapity Slush","Ultimate Burger"],"ratio":"-13.8%","name":"Shipwreck","pirates":["Bonnie Pip Culliford","Orvinn the First Mate","Scurvy Dan the Blade","Ned the Skipper"]},{"foods":["Anchovies","Strochal","Blueberry Tomato Blend","Orange Negg","Fish Negg","Lemon Blitz","Fungi Pizza","Fresh Seaweed Pie","Mustard Ice Cream","Rasmelon"],"ratio":"+23.4%","name":"Lagoon","pirates":["Ol' Stripey","Young Sproggie","Squire Venable","Lucky McKyriggan"]},{"foods":["Joint Of Ham","Rainbow Negg","Fish Negg","Ultimate Burger","Negg Stew","Mustard Ice Cream","Eye Candy","Bacon Muffin","Worm and Leech Pizza","Ice Chocolate Cake"],"ratio":"-13%","name":"Treasure Island","pirates":["Peg Leg Percival","The Tailhook Kid","Captain Crossblades","Admiral Blackbeard"]},{"foods":["Ultimate Burger","Mallowicious Bar","Mustard Ice Cream","Grapity Slush","Anchovies","Hot Cakes","Wriggling Grub","Flaming Burnumup","Fungi Pizza","Worm and Leech Pizza"],"ratio":"-19.6%","name":"Hidden Cove","pirates":["Puffo the Waister","Federismo Corvallio","Franchisco Corvallio","Buck Cutlass"]},{"foods":["Eye Candy","Cinnamon Swirl","Broccoli and Cheese Pizza","Anchovies","Rainborific Slush","Hot Cakes","Rainbow Negg","Fish Negg","Fungi Pizza","Cheese and Tomato Sub"],"ratio":"+36.8%","name":"Harpoon Harry's","pirates":["Sir Edmund Ogletree","Fairfax the Deckhand","Gooblah the Grarrl","Stuff-A-Roo"]}],"round":6145,"pirates":[{"payout":"-12.5%","strength":"","name":"Bonnie Pip Culliford","weight":"","opening":"3:1","current":"3:1","fa":"+3","probability":"29.2%","won":true},{"payout":"-35.0%","strength":"","name":"Orvinn the First Mate","weight":"","opening":"13:1","current":"13:1","fa":"+1","probability":"5.0%","won":false},{"payout":"-13.3%","strength":"","name":"Scurvy Dan the Blade","weight":"","opening":"2:1","current":"2:1","fa":"+0","probability":"43.3%","won":false},{"payout":"-10.0%","strength":"","name":"Ned the Skipper","weight":"","opening":"4:1","current":"4:1","fa":"+0","probability":"22.5%","won":false},{"payout":"+28.3%","strength":"","name":"Ol' Stripey","weight":"","opening":"5:1","current":"7:1","fa":"+1","probability":"18.3%","won":false},{"payout":"+16.1%","strength":"","name":"Young Sproggie","weight":"","opening":"9:1","current":"11:1","fa":"+0","probability":"10.6%","won":false},{"payout":"-35.0%","strength":"","name":"Squire Venable","weight":"","opening":"13:1","current":"13:1","fa":"-2","probability":"5.0%","won":false},{"payout":"+32.2%","strength":"","name":"Lucky McKyriggan","weight":"","opening":"2:1","current":"2:1","fa":"+2","probability":"66.1%","won":true},{"payout":"-8.3%","strength":"","name":"Peg Leg Percival","weight":"","opening":"5:1","current":"5:1","fa":"+0","probability":"18.3%","won":false},{"payout":"-8.3%","strength":"","name":"The Tailhook Kid","weight":"","opening":"5:1","current":"5:1","fa":"-3","probability":"18.3%","won":true},{"payout":"-10.0%","strength":"","name":"Captain Crossblades","weight":"","opening":"4:1","current":"4:1","fa":"+1","probability":"22.5%","won":false},{"payout":"-18.3%","strength":"","name":"Admiral Blackbeard","weight":"","opening":"2:1","current":"2:1","fa":"-1","probability":"40.8%","won":false},{"payout":"-35.0%","strength":"","name":"Puffo the Waister","weight":"","opening":"13:1","current":"13:1","fa":"+0","probability":"5.0%","won":false},{"payout":"-12.5%","strength":"","name":"Federismo Corvallio","weight":"","opening":"3:1","current":"3:1","fa":"+4","probability":"29.2%","won":false},{"payout":"-12.5%","strength":"","name":"Franchisco Corvallio","weight":"","opening":"3:1","current":"3:1","fa":"+2","probability":"29.2%","won":false},{"payout":"-26.7%","strength":"","name":"Buck Cutlass","weight":"","opening":"2:1","current":"2:1","fa":"+0","probability":"36.7%","won":true},{"payout":"-35.0%","strength":"","name":"Sir Edmund Ogletree","weight":"","opening":"13:1","current":"13:1","fa":"-1","probability":"5.0%","won":false},{"payout":"-35.0%","strength":"","name":"Fairfax the Deckhand","weight":"","opening":"13:1","current":"13:1","fa":"+1","probability":"5.0%","won":false},{"payout":"+70.0%","strength":"","name":"Gooblah the Grarrl","weight":"","opening":"2:1","current":"2:1","fa":"+0","probability":"85.0%","won":true},{"payout":"-35.0%","strength":"","name":"Stuff-A-Roo","weight":"","opening":"13:1","current":"13:1","fa":"+0","probability":"5.0%","won":false}]}