{"arenas":[{"foods":["Bubbling Blueberry Pizza","Orange Negg","Rainbow Negg","Hotfish","Worm and Leech Pizza","Eye Candy","Fish Negg","Cheese and Tomato Sub","Grapity Slush","Mallowicious Bar"],"ratio":"-5%","name":"Shipwreck","pirates":["Federismo Corvallio","The Tailhook Kid","Ol' Stripey","Franchisco Corvallio"]},{"foods":["Spicy Wings","Hotfish","Hot Cakes","Ultimate Burger","Bubbling Blueberry Pizza","Strochal","Cheese and Tomato Sub","Anchovies","Eye Candy","Lemon Blitz"],"ratio":"-20%","name":"Lagoon","pirates":["Peg Leg Percival","Puffo the Waister","Young Sproggie","Fairfax the Deckhand"]},{"foods":["Anchovies","Orange Negg","Mallowicious Bar","Mustard Ice Cream","Worm and Leech Pizza","Ice Chocolate Cake","Hot Tyrannian Pepper","Negg Stew","Eye Candy","Ultimate Burger"],"ratio":"+36.8%","name":"Treasure Island","pirates":["Stuff-A-Roo","Ned the Skipper","Gooblah the Grarrl","Captain Crossblades"]},{"foods":["Tangy Tropic Slush","Joint Of Ham","Blueberry Tomato Blend","Wriggling Grub","Anchovies","Super Lemon Grape Slush","Rainborific Slush","Wild Chocomato","Flaming Burnumup","Negg Stew"],"ratio":"-18%","name":"Hidden Cove","pirates":["Admiral Blackbeard","Buck Cutlass","Bonnie Pip Culliford","Lucky McKyriggan"]},{"foods":["Wild Chocomato","Fungi Pizza","Spicy Wings","Broccoli","Asparagus Pie","Bacon Muffin","Streaky Bacon","Super Lemon Grape Slush","Wriggling Grub","Rasmelon"],"ratio":"+30.7%","name":"Harpoon Harry's","pirates":["Orvinn the First Mate","Sir Edmund Ogletree","Scurvy Dan the Blade","Squire Venable"]}],"round":6378,"pirates":[{"payout":"-1.1%","strength":81,"name":"Federismo Corvallio","weight":166,"opening":"2:1","current":"2:1","fa":"+3","probability":"49.4%","won":false},{"payout":"+4.2%","strength":81,"name":"The Tailhook Kid","weight":207,"opening":"12:1","current":"13:1","fa":"-3","probability":"8.0%","won":false},{"payout":"-6.2%","strength":74,"name":"Ol' Stripey","weight":189,"opening":"7:1","current":"7:1","fa":"+1","probability":"13.4%","won":true},{"payout":"-12.5%","strength":81,"name":"Franchisco Corvallio","weight":165,"opening":"3:1","current":"3:1","fa":"-1","probability":"29.2%","won":false},{"payout":"-7.1%","strength":73,"name":"Peg Leg Percival","weight":202,"opening":"6:1","current":"6:1","fa":"+0","probability":"15.5%","won":false},{"payout":"-3.8%","strength":68,"name":"Puffo the Waister","weight":180,"opening":"12:1","current":"12:1","fa":"-1","probability":"8.0%","won":false},{"payout":"-23.5%","strength":73,"name":"Young Sproggie","weight":112,"opening":"2:1","current":"2:1","fa":"+3","probability":"38.3%","won":true},{"payout":"-23.5%","strength":71,"name":"Fairfax the Deckhand","weight":151,"opening":"2:1","current":"2:1","fa":"+1","probability":"38.3%","won":false},{"payout":"-35.0%","strength":59,"name":"Stuff-A-Roo","weight":211,"opening":"13:1","current":"13:1","fa":"-1","probability":"5.0%","won":false},{"payout":"-35.0%","strength":79,"name":"Ned the Skipper","weight":169,"opening":"13:1","current":"13:1","fa":"+1","probability":"5.0%","won":false},{"payout":"+70.0%","strength":93,"name":"Gooblah the Grarrl","weight":199,"opening":"2:1","current":"2:1","fa":"+2","probability":"85.0%","won":true},{"payout":"-35.0%","strength":66,"name":"Captain Crossblades","weight":185,"opening":"13:1","current":"13:1","fa":"+0","probability":"5.0%","won":false},{"payout":"-35.0%","strength":76,"name":"Admiral Blackbeard","weight":171,"opening":"13:1","current":"13:1","fa":"+0","probability":"5.0%","won":false},{"payout":"-18.4%","strength":89,"name":"Buck Cutlass","weight":189,"opening":"2:1","current":"2:1","fa":"-1","probability":"40.8%","won":false},{"payout":"-6.2%","strength":76,"name":"Bonnie Pip Culliford","weight":116,"opening":"7:1","current":"7:1","fa":"+1","probability":"13.4%","won":false},{"payout":"-18.4%","strength":82,"name":"Lucky McKyriggan","weight":182,"opening":"2:1","current":"2:1","fa":"+1","probability":"40.8%","won":true},{"payout":"-35.0%","strength":52,"name":"Orvinn the First Mate","weight":221,"opening":"13:1","current":"13:1","fa":"+2","probability":"5.0%","won":false},{"payout":"+20.5%","strength":79,"name":"Sir Edmund Ogletree","weight":177,"opening":"7:1","current":"9:1","fa":"+1","probability":"13.4%","won":false},{"payout":"+53.2%","strength":87,"name":"Scurvy Dan the Blade","weight":166,"opening":"2:1","current":"2:1","fa":"+3","probability":"76.6%","won":true},{"payout":"-35.0%","strength":61,"name":"Squire Venable","weight":213,"opening":"13:1","current":"13:1","fa":"+1","probability":"5.0%","won":false}]}