{"arenas":[{"foods":[],"ratio":"-2.6%","name":"Shipwreck","pirates":["Ned the Skipper","Squire Venable","Peg Leg Percival","Bonnie Pip Culliford"]},{"foods":[],"ratio":"-10.4%","name":"Lagoon","pirates":["Buck Cutlass","Scurvy Dan the Blade","Young Sproggie","The Tailhook Kid"]},{"foods":[],"ratio":"-16.8%","name":"Treasure Island","pirates":["Ol' Stripey","Lucky McKyriggan","Orvinn the First Mate","Sir Edmund Ogletree"]},{"foods":[],"ratio":"+25.5%","name":"Hidden Cove","pirates":["Admiral Blackbeard","Fairfax the Deckhand","Gooblah the Grarrl","Federismo Corvallio"]},{"foods":[],"ratio":"+28.4%","name":"Harpoon Harry's","pirates":["Puffo the Waister","Captain Crossblades","Franchisco Corvallio","Stuff-A-Roo"]}],"round":6651,"pirates":[{"payout":"-10.0%","strength":"","name":"Ned the Skipper","weight":"","opening":"4:1","current":"4:1","fa":"+0","probability":"22.5%","won":false},{"payout":"-35.0%","strength":"","name":"Squire Venable","weight":"","opening":"13:1","current":"13:1","fa":"-1","probability":"5.0%","won":false},{"payout":"-8.3%","strength":"","name":"Peg Leg Percival","weight":"","opening":"5:1","current":"5:1","fa":"-1","probability":"18.3%","won":false},{"payout":"+8.3%","strength":"","name":"Bonnie Pip Culliford","weight":"","opening":"2:1","current":"2:1","fa":"+2","probability":"54.2%","won":true},{"payout":"-7.1%","strength":"","name":"Buck Cutlass","weight":"","opening":"6:1","current":"6:1","fa":"-2","probability":"15.5%","won":false},{"payout":"-10.0%","strength":"","name":"Scurvy Dan the Blade","weight":"","opening":"4:1","current":"4:1","fa":"-1","probability":"22.5%","won":false},{"payout":"-8.3%","strength":"","name":"Young Sproggie","weight":"","opening":"5:1","current":"5:1","fa":"+2","probability":"18.3%","won":false},{"payout":"-12.6%","strength":"","name":"The Tailhook Kid","weight":"","opening":"2:1","current":"2:1","fa":"+2","probability":"43.7%","won":true},{"payout":"-5.6%","strength":"","name":"Ol' Stripey","weight":"","opening":"8:1","current":"8:1","fa":"+1","probability":"11.8%","won":false},{"payout":"-16.8%","strength":"","name":"Lucky McKyriggan","weight":"","opening":"2:1","current":"2:1","fa":"+0","probability":"41.6%","won":true},{"payout":"-35.0%","strength":"","name":"Orvinn the First Mate","weight":"","opening":"13:1","current":"13:1","fa":"+0","probability":"5.0%","won":false},{"payout":"-16.8%","strength":"","name":"Sir Edmund Ogletree","weight":"","opening":"2:1","current":"2:1","fa":"+0","probability":"41.6%","won":false},{"payout":"-35.0%","strength":"","name":"Admiral Blackbeard","weight":"","opening":"13:1","current":"13:1","fa":"+1","probability":"5.0%","won":false},{"payout":"-35.0%","strength":"","name":"Fairfax the Deckhand","weight":"","opening":"13:1","current":"13:1","fa":"+1","probability":"5.0%","won":false},{"payout":"+43.3%","strength":"","name":"Gooblah the Grarrl","weight":"","opening":"2:1","current":"2:1","fa":"+2","probability":"71.7%","won":true},{"payout":"+28.3%","strength":"","name":"Federismo Corvallio","weight":"","opening":"5:1","current":"7:1","fa":"+0","probability":"18.3%","won":false},{"payout":"+16.1%","strength":"","name":"Puffo the Waister","weight":"","opening":"9:1","current":"11:1","fa":"+1","probability":"10.6%","won":false},{"payout":"+4.2%","strength":"","name":"Captain Crossblades","weight":"","opening":"12:1","current":"13:1","fa":"+0","probability":"8.0%","won":false},{"payout":"+36.1%","strength":"","name":"Franchisco Corvallio","weight":"","opening":"2:1","current":"2:1","fa":"+2","probability":"68.0%","won":true},{"payout":"+20.5%","strength":"","name":"Stuff-A-Roo","weight":"","opening":"7:1","current":"9:1","fa":"+0","probability":"13.4%","won":false}]}