{"arenas":[{"foods":["Hot Cakes","Lemon Blitz","Spicy Wings","Super Lemon Grape Slush","Mustard Ice Cream","Rainbow Negg","Blueberry Tomato Blend","Anchovies","Fungi Pizza","Broccoli"],"ratio":"+1.3%","name":"Shipwreck","pirates":["Squire Venable","Stuff-A-Roo","Lucky McKyriggan","Admiral Blackbeard"]},{"foods":["Streaky Bacon","Bubbling Blueberry Pizza","Fish Negg","Broccoli","Orange Negg","Ice Chocolate Cake","Lemon Blitz","Joint Of Ham","Anchovies","Flaming Burnumup"],"ratio":"+30.7%","name":"Lagoon","pirates":["The Tailhook Kid","Gooblah the Grarrl","Young Sproggie","Sir Edmund Ogletree"]},{"foods":["Orange Negg","Broccoli","Blueberry Tomato Blend","Asparagus Pie","Bubbling Blueberry Pizza","Apple Onion Rings","Fish Negg","Rainborific Slush","Streaky Bacon","Fungi Pizza"],"ratio":"-13.8%","name":"Treasure Island","pirates":["Peg Leg Percival","Buck Cutlass","Fairfax the Deckhand","Franchisco Corvallio"]},{"foods":["Flaming Burnumup","Fungi Pizza","Fish Negg","Mustard Ice Cream","Mallowicious Bar","Asparagus Pie","Hot Tyrannian Pepper","Rainbow Negg","Bubbling Blueberry Pizza","Grapity Slush"],"ratio":"+15.1%","name":"Hidden Cove","pirates":["Federismo Corvallio","Captain Crossblades","Ol' Stripey","Orvinn the First Mate"]},{"foods":["Mustard Ice Cream","Fungi Pizza","Negg Stew","Anchovies","Tangy Tropic Slush","Joint Of Ham","Hotfish","Flaming Burnumup","Streaky Bacon","Hot Tyrannian Pepper"],"ratio":"+30.7%","name":"Harpoon Harry's","pirates":["Ned the Skipper","Puffo the Waister","Scurvy Dan the Blade","Bonnie Pip Culliford"]}],"round":6742,"pirates":[{"payout":"-35.0%","strength":61,"name":"Squire Venable","weight":213,"opening":"13:1","current":"13:1","fa":"-1","probability":"5.0%","won":""},{"payout":"-35.0%","strength":59,"name":"Stuff-A-Roo","weight":211,"opening":"13:1","current":"13:1","fa":"+0","probability":"5.0%","won":""},{"payout":"+21.7%","strength":82,"name":"Lucky McKyriggan","weight":182,"opening":"2:1","current":"2:1","fa":"+1","probability":"60.8%","won":""},{"payout":"-12.5%","strength":76,"name":"Admiral Blackbeard","weight":171,"opening":"3:1","current":"3:1","fa":"+0","probability":"29.2%","won":""},{"payout":"-35.0%","strength":81,"name":"The Tailhook Kid","weight":207,"opening":"13:1","current":"13:1","fa":"+0","probability":"5.0%","won":""},{"payout":"+44.1%","strength":93,"name":"Gooblah the Grarrl","weight":199,"opening":"2:1","current":"2:1","fa":"+3","probability":"72.1%","won":""},{"payout":"+20.5%","strength":73,"name":"Young Sproggie","weight":112,"opening":"7:1","current":"9:1","fa":"+5","probability":"13.4%","won":""},{"payout":"+24.1%","strength":79,"name":"Sir Edmund Ogletree","weight":177,"opening":"10:1","current":"13:1","fa":"+1","probability":"9.5%","won":""},{"payout":"-35.0%","strength":73,"name":"Peg Leg Percival","weight":202,"opening":"13:1","current":"13:1","fa":"-1","probability":"5.0%","won":""},{"payout":"-10.0%","strength":89,"name":"Buck Cutlass","weight":189,"opening":"4:1","current":"4:1","fa":"-2","probability":"22.5%","won":""},{"payout":"-12.5%","strength":71,"name":"Fairfax the Deckhand","weight":151,"opening":"3:1","current":"3:1","fa":"+5","probability":"29.2%","won":""},{"payout":"-13.3%","strength":81,"name":"Franchisco Corvallio","weight":165,"opening":"2:1","current":"2:1","fa":"+1","probability":"43.3%","won":""},{"payout":"+13.3%","strength":81,"name":"Federismo Corvallio","weight":166,"opening":"2:1","current":"2:1","fa":"+3","probability":"56.6%","won":""},{"payout":"+14.5%","strength":66,"name":"Captain Crossblades","weight":185,"opening":"10:1","current":"12:1","fa":"+3","probability":"9.5%","won":""},{"payout":"+28.3%","strength":74,"name":"Ol' Stripey","weight":189,"opening":"5:1","current":"7:1","fa":"+1","probability":"18.3%","won":""},{"payout":"+8.3%","strength":52,"name":"Orvinn the First Mate","weight":221,"opening":"6:1","current":"7:1","fa":"+3","probability":"15.5%","won":""},{"payout":"+20.5%","strength":79,"name":"Ned the Skipper","weight":169,"opening":"7:1","current":"9:1","fa":"+3","probability":"13.4%","won":""},{"payout":"-35.0%","strength":68,"name":"Puffo the Waister","weight":180,"opening":"13:1","current":"13:1","fa":"-3","probability":"5.0%","won":""},{"payout":"+53.2%","strength":87,"name":"Scurvy Dan the Blade","weight":166,"opening":"2:1","current":"2:1","fa":"+4","probability":"76.6%","won":""},{"payout":"-35.0%","strength":76,"name":"Bonnie Pip Culliford","weight":116,"opening":"13:1","current":"13:1","fa":"-2","probability":"5.0%","won":""}]}